lutfiy/__init__.py
lutfiy/api.py
lutfiy/ngram_zwnj.py
lutfiy/transliterate.py
lutfiy/files/ngram_predictor.pkl
lutfiy-0.0.2.dist-info/METADATA
lutfiy-0.0.2.dist-info/WHEEL
lutfiy-0.0.2.dist-info/licenses/LICENSE
lutfiy-0.0.2.dist-info/RECORD
