Metadata-Version: 2.4
Name: lutfiy
Version: 0.0.2
Summary: lutfiy - transliteration and zwnj scripts for Southern Uzbek
Project-URL: Homepage, https://github.com/tahrirchi/uzs-scripts
Project-URL: Bug Tracker, https://github.com/tahrirchi/uzs-scripts/issues
Author-email: Muhammadsaid Mamasaidov <mukhammadsaid.mamasaidov@gmail.com>, Abror Shopulatov <murodbeck@proton.me>
Maintainer-email: Muhammadsaid Mamasaidov <mukhammadsaid.mamasaidov@gmail.com>, Abror Shopulatov <murodbeck@proton.me>
License: MIT License
License-File: LICENSE
Keywords: language,transliteration,uzs,zwnj
Classifier: License :: OSI Approved :: MIT License
Classifier: Operating System :: POSIX
Classifier: Programming Language :: Python :: 3
Classifier: Topic :: Text Processing :: Linguistic
Requires-Python: >=3.6
